{
  "code": "600001",
  "klines": [
    {
      "date": "2026-06-01",
      "open": 10,
      "close": 8.8,
      "high": 11,
      "low": 9,
      "volume": 1000000
    },
    {
      "date": "2026-06-02",
      "open": 10,
      "close": 8.95,
      "high": 11,
      "low": 9,
      "volume": 1000000
    },
    {
      "date": "2026-06-03",
      "open": 10,
      "close": 9.1,
      "high": 11,
      "low": 9,
      "volume": 1000000
    },
    {
      "date": "2026-06-04",
      "open": 10,
      "close": 9.25,
      "high": 11,
      "low": 9,
      "volume": 1000000
    },
    {
      "date": "2026-06-05",
      "open": 10,
      "close": 9.4,
      "high": 11,
      "low": 9,
      "volume": 1000000
    },
    {
      "date": "2026-06-08",
      "open": 10,
      "close": 9.85,
      "high": 11,
      "low": 9,
      "volume": 1000000
    },
    {
      "date": "2026-06-09",
      "open": 10,
      "close": 10,
      "high": 11,
      "low": 9,
      "volume": 1000000
    },
    {
      "date": "2026-06-10",
      "open": 10,
      "close": 10.15,
      "high": 11,
      "low": 9,
      "volume": 1000000
    },
    {
      "date": "2026-06-11",
      "open": 10,
      "close": 10.3,
      "high": 11,
      "low": 9,
      "volume": 1000000
    },
    {
      "date": "2026-06-12",
      "open": 10,
      "close": 10.45,
      "high": 11,
      "low": 9,
      "volume": 1000000
    },
    {
      "date": "2026-06-15",
      "open": 10,
      "close": 10.9,
      "high": 11,
      "low": 9,
      "volume": 1000000
    },
    {
      "date": "2026-06-16",
      "open": 10,
      "close": 11.05,
      "high": 11,
      "low": 9,
      "volume": 1000000
    },
    {
      "date": "2026-06-17",
      "open": 10,
      "close": 11.2,
      "high": 11,
      "low": 9,
      "volume": 1000000
    },
    {
      "date": "2026-06-18",
      "open": 10,
      "close": 11.35,
      "high": 11,
      "low": 9,
      "volume": 1000000
    },
    {
      "date": "2026-06-19",
      "open": 10,
      "close": 11.5,
      "high": 11,
      "low": 9,
      "volume": 1000000
    }
  ]
}